tequila/__init__.py
tequila/autograd_imports.py
tequila/version.py
tequila/apps/__init__.py
tequila/apps/_unary_state_prep_impl.py
tequila/apps/unary_state_prep.py
tequila/apps/adapt/__init__.py
tequila/apps/adapt/adapt.py
tequila/apps/krylov/__init__.py
tequila/apps/krylov/krylov.py
tequila/apps/robustness/__init__.py
tequila/apps/robustness/helpers.py
tequila/apps/robustness/interval.py
tequila/circuit/__init__.py
tequila/circuit/_gates_impl.py
tequila/circuit/circuit.py
tequila/circuit/compiler.py
tequila/circuit/gates.py
tequila/circuit/gradient.py
tequila/circuit/noise.py
tequila/circuit/postselection.py
tequila/circuit/pyzx.py
tequila/circuit/qasm.py
tequila/circuit/qpic.py
tequila/grouping/__init__.py
tequila/grouping/binary_rep.py
tequila/grouping/binary_utils.py
tequila/grouping/compile_groups.py
tequila/grouping/ev_utils.py
tequila/grouping/fermionic_functions.py
tequila/grouping/fermionic_methods.py
tequila/grouping/overlapping_methods.py
tequila/hamiltonian/__init__.py
tequila/hamiltonian/paulis.py
tequila/hamiltonian/paulistring.py
tequila/hamiltonian/qubit_hamiltonian.py
tequila/ml/__init__.py
tequila/ml/interface_torch.py
tequila/ml/ml_api.py
tequila/ml/utils_ml.py
tequila/objective/__init__.py
tequila/objective/braket.py
tequila/objective/objective.py
tequila/objective/qtensor.py
tequila/optimizers/__init__.py
tequila/optimizers/_containers.py
tequila/optimizers/optimizer_base.py
tequila/optimizers/optimizer_gd.py
tequila/optimizers/optimizer_gpyopt.py
tequila/optimizers/optimizer_scipy.py
tequila/quantumchemistry/__init__.py
tequila/quantumchemistry/chemistry_tools.py
tequila/quantumchemistry/encodings.py
tequila/quantumchemistry/madness_interface.py
tequila/quantumchemistry/orbital_optimizer.py
tequila/quantumchemistry/psi4_interface.py
tequila/quantumchemistry/pyscf_interface.py
tequila/quantumchemistry/qc_base.py
tequila/simulators/__init__.py
tequila/simulators/simulator_api.py
tequila/simulators/simulator_aqt.py
tequila_basic-1.9.10.dist-info/licenses/LICENSE
tequila_basic-1.9.10.dist-info/METADATA
tequila_basic-1.9.10.dist-info/WHEEL
tequila_basic-1.9.10.dist-info/top_level.txt
tequila_basic-1.9.10.dist-info/RECORD
