Metadata-Version: 2.4
Name: tequila-basic
Version: 1.9.10
Summary: A High-Level Abstraction Framework for Quantum Algorithms
Home-page: https://github.com/tequilahub/tequila
Author: Tequila Developers 
Author-email: jakob.kottmann@gmail.com
License-File: LICENSE
Requires-Dist: numpy
Requires-Dist: scipy
Requires-Dist: sympy
Requires-Dist: autograd
Requires-Dist: setuptools
Requires-Dist: pytest
Requires-Dist: openfermion~=1.0
Requires-Dist: dataclasses; python_version < "3.7"
Dynamic: author
Dynamic: author-email
Dynamic: description
Dynamic: description-content-type
Dynamic: home-page
Dynamic: license-file
Dynamic: provides-extra
Dynamic: requires-dist
Dynamic: summary
